soaplib/__init__.py
soaplib/client.py
soaplib/easy_client.py
soaplib/etimport.py
soaplib/service.py
soaplib/soap.py
soaplib/util.py
soaplib/wsgi_soap.py
soaplib/xml.py
soaplib/zope2.py
soaplib/ext/__init__.py
soaplib/ext/comproxy.py
soaplib/parsers/__init__.py
soaplib/parsers/typeparse.py
soaplib/parsers/wsdlparse.py
soaplib/serializers/__init__.py
soaplib/serializers/binary.py
soaplib/serializers/clazz.py
soaplib/serializers/primitive.py
tests/serializers/__init__.py
tests/serializers/binary_test.py
tests/serializers/clazz_test.py
tests/serializers/include_test.py
tests/serializers/primitive_test.py
soaplib_mpsinfo-0.10.0.dist-info/LICENSE
soaplib_mpsinfo-0.10.0.dist-info/METADATA
soaplib_mpsinfo-0.10.0.dist-info/WHEEL
soaplib_mpsinfo-0.10.0.dist-info/entry_points.txt
soaplib_mpsinfo-0.10.0.dist-info/top_level.txt
soaplib_mpsinfo-0.10.0.dist-info/RECORD
