Metadata-Version: 2.1
Name: soaplib-mpsinfo
Version: 0.10.0
Summary: A simple library for writing soap web services
Home-page: https://github.com/mpsinfo/soaplib/tree/master
Author: MPS Informática Ltda.
Author-email: gti@mps.com.br
Maintainer: Carlos Alberto Costa Beppler
Maintainer-email: carlos.beppler@mps.com.br
License: LGPL
Keywords: soap
Platform: UNKNOWN
Classifier: Programming Language :: Python
Classifier: Operating System :: OS Independent
Classifier: Natural Language :: English
Classifier: Development Status :: 4 - Beta
Classifier: Intended Audience :: Developers
Classifier: Topic :: Internet :: WWW/HTTP :: Dynamic Content
Requires-Dist: pytz
Requires-Dist: lxml (>=2.2.1)
